cloudmappings/__init__.py
cloudmappings/_cloudmappinginternal.py
cloudmappings/cloudmapping.py
cloudmappings/cloudstorage.py
cloudmappings/errors.py
cloudmappings/storageprovider.py
cloudmappings/_storageproviders/__init__.py
cloudmappings/_storageproviders/awss3storage.py
cloudmappings/_storageproviders/azureblobstorage.py
cloudmappings/_storageproviders/azuretablestorage.py
cloudmappings/_storageproviders/googlecloudstorage.py
cloudmappings/serialisers/__init__.py
cloudmappings/serialisers/core.py
cloudmappings/serialisers/pandas.py
cloudmappings/serialisers/serialisation.py
cloud_mappings-2.1.0.dist-info/LICENSE
cloud_mappings-2.1.0.dist-info/METADATA
cloud_mappings-2.1.0.dist-info/WHEEL
cloud_mappings-2.1.0.dist-info/top_level.txt
cloud_mappings-2.1.0.dist-info/RECORD
