Metadata-Version: 2.1
Name: cloud-mappings
Version: 2.1.0
Summary: MutableMapping interfaces for common cloud storage providers
Home-page: https://github.com/JJ11teen/cloud-mappings
Author: Lucas Sargent
Author-email: lucas.sargent@outlook.com
Project-URL: Bug Tracker, https://github.com/JJ11teen/cloud-mappings/issues
Keywords: mutable dict aws s3 azure gcp
Classifier: Programming Language :: Python :: 3
Classifier: License :: OSI Approved :: MIT License
Classifier: Operating System :: OS Independent
Requires-Python: >=3.7
License-File: LICENSE
Provides-Extra: awss3
Requires-Dist: boto3 (==1.26.129) ; extra == 'awss3'
Provides-Extra: azureblob
Requires-Dist: azure-identity (==1.12.0) ; extra == 'azureblob'
Requires-Dist: azure-storage-blob (==12.16.0) ; extra == 'azureblob'
Provides-Extra: azuretable
Requires-Dist: azure-identity (==1.12.0) ; extra == 'azuretable'
Requires-Dist: azure-data-tables (==12.4.2) ; extra == 'azuretable'
Provides-Extra: gcpstorage
Requires-Dist: google-cloud-storage (==2.9.0) ; extra == 'gcpstorage'
Provides-Extra: tests
Requires-Dist: pytest (==7.1.2) ; extra == 'tests'
Requires-Dist: pytest-mock (==3.1.0) ; extra == 'tests'
